Metadata-Version: 2.1
Name: hgfinance
Version: 0.0.7
Summary: Um pacote que facilita o acesso à API HG finance.
Home-page: https://github.com/resilientcod/hgfinance-python
Author: José Almir
Author-email: resilientcod@gmail.com
License: MIT
Keywords: api hgfinance currency quotation selic cdi dollar hgbrasil
Platform: UNKNOWN
Classifier: Programming Language :: Python :: 3
Classifier: License :: OSI Approved :: MIT License
Classifier: Operating System :: OS Independent
Classifier: Natural Language :: Portuguese (Brazilian)
